{
	"name": "13_create_silver_views",
	"properties": {
		"folder": {
			"name": "ldw"
		},
		"content": {
			"query": "USE nyc_taxi_ldw\nGO \n\n-- Create view for trip_data_green\nDROP VIEW IF EXISTS silver.vw_trip_data_green\nGO\n\nCREATE VIEW silver.vw_trip_data_green\nAS\nSELECT\n    result.filepath(1) AS year,\n    result.filepath(2) AS month,\n    result.*\nFROM\n    OPENROWSET(\n        BULK 'silver/trip_data_green/year=*/month=*/*.parquet',\n        DATA_SOURCE = 'nyc_taxi_src',\n        FORMAT = 'PARQUET'\n    )\n    WITH (\n        vendor_id INT,\n        lpep_pickup_datetime datetime2(7),\n        lpep_dropoff_datetime datetime2(7),\n        store_and_fwd_flag CHAR(1),\n        rate_code_id INT,\n        pu_location_id INT,\n        do_location_id INT,\n        passenger_count INT,\n        trip_distance FLOAT,\n        fare_amount FLOAT,\n        extra FLOAT,\n        mta_tax FLOAT,\n        tip_amount FLOAT,\n        tolls_amount FLOAT,\n        ehail_fee INT,\n        improvement_surcharge FLOAT,\n        total_amount FLOAT,\n        payment_type INT,\n        trip_type INT,\n        congestion_surcharge FLOAT\n  ) AS [result]\nGO\n\nSELECT TOP(100) *\n  FROM silver.vw_trip_data_green\nGO",
			"metadata": {
				"language": "sql"
			},
			"currentConnection": {
				"databaseName": "nyc_taxi_ldw",
				"poolName": "Built-in"
			},
			"resultLimit": 5000
		},
		"type": "SqlQuery"
	}
}